ChengzhenMishangwoHexinJiangcheng/README.md
ChengzhenMishangwoHexinJiangcheng/__init__.py
ChengzhenMishangwoHexinJiangcheng/__main__.py
ChengzhenMishangwoHexinJiangcheng/file.epub
ChengzhenMishangwoHexinJiangcheng/index.html
ChengzhenMishangwoHexinJiangcheng/css/__init__.py
ChengzhenMishangwoHexinJiangcheng/css/annotations.css
ChengzhenMishangwoHexinJiangcheng/css/main.css
ChengzhenMishangwoHexinJiangcheng/css/normalize.css
ChengzhenMishangwoHexinJiangcheng/css/popup.css
ChengzhenMishangwoHexinJiangcheng/font/__init__.py
ChengzhenMishangwoHexinJiangcheng/font/fontello.eot
ChengzhenMishangwoHexinJiangcheng/font/fontello.svg
ChengzhenMishangwoHexinJiangcheng/font/fontello.ttf
ChengzhenMishangwoHexinJiangcheng/font/fontello.woff
ChengzhenMishangwoHexinJiangcheng/img/__init__.py
ChengzhenMishangwoHexinJiangcheng/img/annotator-glyph-sprite.png
ChengzhenMishangwoHexinJiangcheng/img/annotator-icon-sprite.png
ChengzhenMishangwoHexinJiangcheng/img/apple-touch-icon.png
ChengzhenMishangwoHexinJiangcheng/img/cancelfullscreen.png
ChengzhenMishangwoHexinJiangcheng/img/close.png
ChengzhenMishangwoHexinJiangcheng/img/fullscreen.png
ChengzhenMishangwoHexinJiangcheng/img/loader.gif
ChengzhenMishangwoHexinJiangcheng/img/menu-icon.png
ChengzhenMishangwoHexinJiangcheng/img/save.png
ChengzhenMishangwoHexinJiangcheng/img/saved.png
ChengzhenMishangwoHexinJiangcheng/img/settings-s.png
ChengzhenMishangwoHexinJiangcheng/img/settings.png
ChengzhenMishangwoHexinJiangcheng/img/star.png
ChengzhenMishangwoHexinJiangcheng/js/__init__.py
ChengzhenMishangwoHexinJiangcheng/js/epub.js
ChengzhenMishangwoHexinJiangcheng/js/epub.min.js
ChengzhenMishangwoHexinJiangcheng/js/epub.min.map
ChengzhenMishangwoHexinJiangcheng/js/hooks.min.js
ChengzhenMishangwoHexinJiangcheng/js/hooks.min.map
ChengzhenMishangwoHexinJiangcheng/js/reader.js
ChengzhenMishangwoHexinJiangcheng/js/reader.js.map
ChengzhenMishangwoHexinJiangcheng/js/reader.min.js
ChengzhenMishangwoHexinJiangcheng/js/reader.min.map
chengzhen_mishangwo_hexin_jiangcheng-2022.10.11.0.dist-info/METADATA
chengzhen_mishangwo_hexin_jiangcheng-2022.10.11.0.dist-info/WHEEL
chengzhen_mishangwo_hexin_jiangcheng-2022.10.11.0.dist-info/entry_points.txt
chengzhen_mishangwo_hexin_jiangcheng-2022.10.11.0.dist-info/top_level.txt
chengzhen_mishangwo_hexin_jiangcheng-2022.10.11.0.dist-info/RECORD
